LICENSE.txt
README.txt
setup.py
games_g/__init__.py
games_g.egg-info/PKG-INFO
games_g.egg-info/SOURCES.txt
games_g.egg-info/dependency_links.txt
games_g.egg-info/not-zip-safe
games_g.egg-info/requires.txt
games_g.egg-info/top_level.txt