Metadata-Version: 2.1
Name: games_g
Version: 2.9.1
Summary: Console Based Guess the Number and Snake and Ladder Game.
Author: Ghanshyam Vaja
Author-email: ghanshyamvaja11@gmail.com
License: MIT
Keywords: gmaes_g,g games
Classifier: Development Status :: 5 - Production/Stable
Classifier: License :: OSI Approved :: MIT License
Classifier: Programming Language :: Python :: 3.10
Requires-Python: >=3.6
License-File: LICENSE.txt
Requires-Dist: pyttsx3>=2.90
Requires-Dist: pyaudio
